[
  {
    "full_name": "GoogleChrome/lighthouse",
    "stargazers_count": 23927,
    "open_issues_count": 565,
    "forks_count": 8298
  },
  {
    "full_name": "responsively-org/responsively-app",
    "stargazers_count": 14498,
    "open_issues_count": 107,
    "forks_count": 622
  },
  {
    "full_name": "open-sauced/open-sauced",
    "stargazers_count": 556,
    "open_issues_count": 29,
    "forks_count": 158
  },
  {
    "full_name": "Serial-Studio/Serial-Studio",
    "stargazers_count": 1963,
    "open_issues_count": 11,
    "forks_count": 237
  },
  {
    "full_name": "oppia/oppia",
    "stargazers_count": 4368,
    "open_issues_count": 1245,
    "forks_count": 2217
  },
  {
    "full_name": "backstage/backstage",
    "stargazers_count": 14416,
    "open_issues_count": 394,
    "forks_count": 1946
  },
  {
    "full_name": "jupyterlab/jupyterlab",
    "stargazers_count": 11689,
    "open_issues_count": 2038,
    "forks_count": 2193
  },
  {
    "full_name": "withspectrum/spectrum",
    "stargazers_count": 10318,
    "open_issues_count": 267,
    "forks_count": 1184
  },
  {
    "full_name": "gitcoinco/web",
    "stargazers_count": 1428,
    "open_issues_count": 480,
    "forks_count": 740
  }
]